simple_pass_manager/__init__.py
simple_pass_manager/exceptions.py
simple_pass_manager/manager.py
simple_pass_manager/utils/__init__.py
simple_pass_manager/utils/encryption.py
simple_pass_manager/utils/generation.py
simple_pass_manager/utils/encryption/__init__.py
simple_pass_manager/utils/encryption/encryption.py
simple_pass_manager/utils/generation/__init__.py
simple_pass_manager/utils/generation/generation.py
simple_pass_manager-0.0.8.dist-info/METADATA
simple_pass_manager-0.0.8.dist-info/WHEEL
simple_pass_manager-0.0.8.dist-info/top_level.txt
simple_pass_manager-0.0.8.dist-info/RECORD
