Metadata-Version: 2.1
Name: simple-pass-manager
Version: 0.0.8
Summary: small description like my d
Author: Zhmishenko Valery Albertovic
Author-email: my_real_email@motoblock.com
License: UNKNOWN
Platform: UNKNOWN
Requires-Python: >=3.9.7
Requires-Dist: cryptography
